MANIFEST.in
README.md
setup.py
sortedm2m_horizontal_widget/__init__.py
sortedm2m_horizontal_widget/forms.py
sortedm2m_horizontal_widget.egg-info/PKG-INFO
sortedm2m_horizontal_widget.egg-info/SOURCES.txt
sortedm2m_horizontal_widget.egg-info/dependency_links.txt
sortedm2m_horizontal_widget.egg-info/not-zip-safe
sortedm2m_horizontal_widget.egg-info/requires.txt
sortedm2m_horizontal_widget.egg-info/top_level.txt
sortedm2m_horizontal_widget/static/sortedm2m_horizontal_widget/OrderedSelectBox.js
sortedm2m_horizontal_widget/static/sortedm2m_horizontal_widget/OrderedSelectFilter.js
sortedm2m_horizontal_widget/static/sortedm2m_horizontal_widget/selector-down.gif
sortedm2m_horizontal_widget/static/sortedm2m_horizontal_widget/selector-up.gif
sortedm2m_horizontal_widget/static/sortedm2m_horizontal_widget/widget.css