Metadata-Version: 1.1
Name: sortedm2m-horizontal-widget
Version: 0.5.0
Summary: Horizontal filter widget for django-sortedm2m
Home-page: https://github.com/svleeuwen/sortedm2m-filter-horizontal-widget
Author: Sander van Leeuwen
Author-email: replytosander@gmail.com
License: BSD
Platform: UNKNOWN
Classifier: Development Status :: 4 - Beta
Classifier: Environment :: Web Environment
Classifier: Framework :: Django
Classifier: Intended Audience :: Developers
Classifier: License :: OSI Approved :: BSD License
Classifier: Natural Language :: English
Classifier: Operating System :: OS Independent
Classifier: Programming Language :: Python :: 2.7
Classifier: Programming Language :: Python :: 3.5
